{
  "info": {
    "book": "Salmos",
    "chapter": "100",
    "translation": "Sagradas Escrituras",
    "translationID": "se",
    "language": "Español",
    "languageID": "es"
  },
  "data": {
    "1": {
      "text": "¶ Salmo para confesión. Cantad a Dios con júbilo, toda la tierra.",
      "topic": ""
    },
    "2": {
      "text": "Servid al SEÑOR con alegría; entrad delante de él con regocijo.",
      "topic": ""
    },
    "3": {
      "text": "Reconoced que el SEÑOR es el Dios: él nos hizo, y no nosotros a nosotros mismos . Pueblo suyo somos , y ovejas de su prado.",
      "topic": ""
    },
    "4": {
      "text": "Entrad por sus puertas con confesión; por sus atrios con alabanza; alabadle, bendecid su Nombre.",
      "topic": ""
    },
    "5": {
      "text": "Porque el SEÑOR es bueno; para siempre es su misericordia, y su verdad por todas las generaciones.",
      "topic": ""
    }
  }
}