{
  "info": {
    "book": "Salmos",
    "chapter": "54",
    "translation": "Sagradas Escrituras",
    "translationID": "se",
    "language": "Español",
    "languageID": "es"
  },
  "data": {
    "1": {
      "text": "¶ Al Vencedor: en Neginot: Masquil de David, cuando vinieron los zifeos y dijeron a Saúl: ¿No está David escondido en nuestra tierra? Oh Dios, sálvame en tu Nombre, y con tu valentía defiéndeme.",
      "topic": ""
    },
    "2": {
      "text": "Oh Dios, oye mi oración; escucha las razones de mi boca.",
      "topic": ""
    },
    "3": {
      "text": "Porque extraños se han levantado contra mí, y fuertes buscan mi alma; no han puesto a Dios delante de sí. (Selah.)",
      "topic": ""
    },
    "4": {
      "text": "¶ He aquí, Dios es el que me ayuda; el Señor es con los que sustentan mi alma.",
      "topic": ""
    },
    "5": {
      "text": "El volverá el mal a mis enemigos; córtalos por tu verdad.",
      "topic": ""
    },
    "6": {
      "text": "Voluntariamente sacrificaré a ti; alabaré tu Nombre, oh SEÑOR, porque es bueno.",
      "topic": ""
    },
    "7": {
      "text": "Porque me ha librado de toda angustia, y sobre mis enemigos vieron mis ojos el deseo de El .",
      "topic": ""
    }
  }
}